rdkit_headers/__init__.py
rdkit_headers/include/rdkit/RingDecomposerLib.h
rdkit_headers/include/rdkit/Catalogs/Catalog.h
rdkit_headers/include/rdkit/Catalogs/CatalogEntry.h
rdkit_headers/include/rdkit/Catalogs/CatalogParams.h
rdkit_headers/include/rdkit/ChemicalFeatures/ChemicalFeature.h
rdkit_headers/include/rdkit/ChemicalFeatures/FreeChemicalFeature.h
rdkit_headers/include/rdkit/DataManip/MetricMatrixCalc/MetricFuncs.h
rdkit_headers/include/rdkit/DataManip/MetricMatrixCalc/MetricMatrixCalc.h
rdkit_headers/include/rdkit/DataStructs/BitOps.h
rdkit_headers/include/rdkit/DataStructs/BitVect.h
rdkit_headers/include/rdkit/DataStructs/BitVectUtils.h
rdkit_headers/include/rdkit/DataStructs/BitVects.h
rdkit_headers/include/rdkit/DataStructs/DatastructsException.h
rdkit_headers/include/rdkit/DataStructs/DatastructsStreamOps.h
rdkit_headers/include/rdkit/DataStructs/DiscreteDistMat.h
rdkit_headers/include/rdkit/DataStructs/DiscreteValueVect.h
rdkit_headers/include/rdkit/DataStructs/ExplicitBitVect.h
rdkit_headers/include/rdkit/DataStructs/FPBReader.h
rdkit_headers/include/rdkit/DataStructs/MultiFPBReader.h
rdkit_headers/include/rdkit/DataStructs/RealValueVect.h
rdkit_headers/include/rdkit/DataStructs/SparseBitVect.h
rdkit_headers/include/rdkit/DataStructs/SparseIntVect.h
rdkit_headers/include/rdkit/DataStructs/base64.h
rdkit_headers/include/rdkit/DistGeom/BoundsMatrix.h
rdkit_headers/include/rdkit/DistGeom/ChiralSet.h
rdkit_headers/include/rdkit/DistGeom/ChiralViolationContribs.h
rdkit_headers/include/rdkit/DistGeom/DistGeomUtils.h
rdkit_headers/include/rdkit/DistGeom/DistViolationContribs.h
rdkit_headers/include/rdkit/DistGeom/FourthDimContribs.h
rdkit_headers/include/rdkit/DistGeom/TriangleSmooth.h
rdkit_headers/include/rdkit/Features/Feature.h
rdkit_headers/include/rdkit/ForceField/AngleConstraint.h
rdkit_headers/include/rdkit/ForceField/AngleConstraints.h
rdkit_headers/include/rdkit/ForceField/Contrib.h
rdkit_headers/include/rdkit/ForceField/DistanceConstraint.h
rdkit_headers-2025.9.3.post1.dist-info/licenses/LICENSE
rdkit_headers-2025.9.3.post1.dist-info/METADATA
rdkit_headers-2025.9.3.post1.dist-info/WHEEL
rdkit_headers-2025.9.3.post1.dist-info/top_level.txt
rdkit_headers-2025.9.3.post1.dist-info/RECORD
