Metadata-Version: 2.4
Name: rdkit-headers
Version: 2025.9.3.post1
Summary: RDKit headers.
Requires-Python: >=3.9
License-File: LICENSE
Requires-Dist: boost-headers==1.81.0
Requires-Dist: numpy<2.0
Requires-Dist: rdkit==2025.09.3
Provides-Extra: dev
Requires-Dist: pytest; extra == "dev"
Dynamic: license-file
